<?xml version="1.0" encoding="UTF-8" standalone="yes"?>




 
<item>
<title>[COLOR cyan] SERIES PT [/COLOR]</title>
<thumbnail>https://www.gl-assessment.co.uk/media/1299/pt_series-logo.png</thumbnail>
<fanart>https://4.bp.blogspot.com/-lmk22huxzP0/V9FU7r_I2YI/AAAAAAAAG4o/8kyPs8Hcs-QZ4_UUTioM0w2DV4MfLOcYwCLcB/s640/Tuga%2BStreams%2Blive%2Btv%2Baddon.png</fanart>
<link>http://ignorame</link>
<externallink>https://raw.githubusercontent.com/b64decode/-base64/master/SUB-MENUS/MAIS%20IPTV/SERIES%20PT.xml</externallink>
</item>



<item>
<title>[COLOR cyan] BRAZIL TV [/COLOR] </title>
<thumbnail>https://lh3.googleusercontent.com/EQLp_ZRRv6McJNZbqjvk-jifPFARqu5dPd7DYNSC5r9lPuuYSi5fASkZSYg-y3fvE8Q=w300</thumbnail>
<fanart>https://www.rapidtvnews.com/images/pantalla-tv.jpg</fanart>
<link>http://ignorame</link>
<externallink>https://raw.githubusercontent.com/b64decode/-base64/master/SUB-MENUS/MAIS%20IPTV/BRAZIL.xml</externallink>
</item>



<item>
<title>[COLOR cyan] ESPANHA TV [/COLOR]</title>
<thumbnail>http://opendatabarometer.org/data-explorer/img/flags/es.svg</thumbnail>
<fanart>https://upload.wikimedia.org/wikipedia/en/thumb/9/9a/Flag_of_Spain.svg/1280px-Flag_of_Spain.svg.png</fanart>
<link>http://ignorame</link>
<externallink>https://raw.githubusercontent.com/b64decode/-base64/master/SUB-MENUS/MAIS%20IPTV/ESPANHA.xml</externallink>
</item>



<item>
<title>[COLOR cyan] ITALIE TV [/COLOR]</title>
<thumbnail>https://image.spreadshirtmedia.net/image-server/v1/compositions/22118785/views/1,width=300,height=300,version=1478003241/flag-italia-dd-t-shirts-mannen-t-shirt.jpg</thumbnail>
<fanart>https://s-media-cache-ak0.pinimg.com/736x/6e/e5/be/6ee5becb7d126aead06739bf7c91e45b.jpg</fanart>
<link>http://ignorame</link>
<externallink>https://raw.githubusercontent.com/b64decode/-base64/master/SUB-MENUS/MAIS%20IPTV/ITALIE.xml</externallink>
</item>



